dora_microphone/__init__.py
dora_microphone/main.py
dora_microphone-0.4.1.dist-info/METADATA
dora_microphone-0.4.1.dist-info/WHEEL
dora_microphone-0.4.1.dist-info/entry_points.txt
dora_microphone-0.4.1.dist-info/top_level.txt
dora_microphone-0.4.1.dist-info/RECORD
