Metadata-Version: 2.4
Name: dora-microphone
Version: 0.4.1
Summary: Dora dora-microphone
Author-email: Haixuan Xavier Tao <tao.xavier@outlook.com>, Enzo Le Van <dev@enzo-le-van.fr>
License: MIT
Requires-Python: >=3.8
Requires-Dist: dora-rs>=0.3.9
Requires-Dist: numpy<2.0.0
Requires-Dist: pyarrow>=5.0.0
Requires-Dist: sounddevice>=0.4.6
